{
    "date":[
        {
            "id":"1",
            "avatar":"http://",
            "name":"John Smith",
            "tell": "4357589775",
            "email":"john@",
            "city":"London",
            "status":"false"
        },
        {
            "id":"2",
            "avatar":"http://",
            "name":"John Smith",
            "tell": "4357589775",
            "email":"john@",
            "city":"London",
            "status":"false"
        },
        {
            "id":"3",
            "avatar":"http://",
            "name":"John Smith",
            "tell": "4357589775",
            "email":"john@",
            "city":"London",
            "status":"false"
        },
        {
            "id":"4",
            "avatar":"http://",
            "name":"John Smith",
            "tell": "4357589775",
            "email":"john@",
            "city":"London",
            "status":"false"
        }
    ]
}